Metadata-Version: 2.1
Name: pynuoadmin
Version: 2.5.0
Summary: Python management interface for NuoDB
Home-page: https://3ds.com/nuodb-distributed-sql-database
Author: Dassault Systemes SE
Author-email: NuoDB.Support@3ds.com
License: BSD License
Platform: UNKNOWN
Classifier: Development Status :: 5 - Production/Stable
Classifier: Environment :: Console
Classifier: Intended Audience :: Developers
Classifier: Intended Audience :: System Administrators
Classifier: License :: OSI Approved :: BSD License
Classifier: Operating System :: OS Independent
Classifier: Programming Language :: Python
Classifier: Programming Language :: Python :: 2
Classifier: Programming Language :: Python :: 2.7
Classifier: Programming Language :: Python :: 3
Classifier: Programming Language :: Python :: 3.6
Classifier: Programming Language :: Python :: 3.7
Classifier: Programming Language :: Python :: 3.8
Classifier: Programming Language :: Python :: 3.9
Classifier: Programming Language :: Python :: 3.10
Classifier: Programming Language :: SQL
Classifier: Topic :: Database
Provides-Extra: completion
Provides-Extra: crypto
